Cryptronics/__init__.py
Cryptronics/base_crypto.py
Cryptronics/coins/__init__.py
Cryptronics/coins/bnb.py
Cryptronics/coins/btc.py
Cryptronics/coins/custom_types.py
Cryptronics/coins/doge.py
Cryptronics/coins/eth.py
Cryptronics/coins/ltc.py
Cryptronics/coins/trx.py
Cryptronics/coins/xmr.py
Cryptronics/crypto_types.py
Cryptronics/exceptions.py
Cryptronics/injection_detector.py
Cryptronics/mixer.py
cryptronics-1.4.dist-info/WHEEL
cryptronics-1.4.dist-info/METADATA
cryptronics-1.4.dist-info/RECORD
