Metadata-Version: 2.1
Name: cryptronics
Version: 1.4
Summary: Easy to use crypto API for python.
Author: vsaverin
Author-email: vasiliy.saverin@gmail.com
Requires-Python: >=3.9,<4.0
Classifier: Programming Language :: Python :: 3
Classifier: Programming Language :: Python :: 3.9
Classifier: Programming Language :: Python :: 3.10
Classifier: Programming Language :: Python :: 3.11
Requires-Dist: bit (>=0.8.0,<0.9.0)
Requires-Dist: bitcoin (>=1.1.42,<2.0.0)
Requires-Dist: kucoin-python (>=1.0.11,<2.0.0)
Requires-Dist: litecoin-utils (>=0.5.4,<0.6.0)
Requires-Dist: monero (>=1.1.1,<2.0.0)
Requires-Dist: python-dogecoin (>=0.0.4,<0.0.5)
Requires-Dist: tronapi (>=3.1.6,<4.0.0)
